switchbotmeter/__about__.py
switchbotmeter/__init__.py
switchbotmeter-1.1.0.dist-info/METADATA
switchbotmeter-1.1.0.dist-info/WHEEL
switchbotmeter-1.1.0.dist-info/licenses/LICENSE
switchbotmeter-1.1.0.dist-info/RECORD
