Metadata-Version: 2.1
Name: switchbotmeter
Version: 1.1.0
Project-URL: Documentation, https://github.com/unknown/switchbotmeter#readme
Project-URL: Issues, https://github.com/unknown/switchbotmeter/issues
Project-URL: Source, https://github.com/unknown/switchbotmeter
Author-email: David Francos <me@davidfrancos.net>
License-Expression: GPL-3.0
License-File: LICENSE
Classifier: Development Status :: 4 - Beta
Classifier: Programming Language :: Python
Classifier: Programming Language :: Python :: 3.8
Classifier: Programming Language :: Python :: 3.9
Classifier: Programming Language :: Python :: 3.10
Classifier: Programming Language :: Python :: 3.11
Classifier: Programming Language :: Python :: Implementation :: CPython
Classifier: Programming Language :: Python :: Implementation :: PyPy
Requires-Python: >=3.7
Requires-Dist: bluepy~=1.3.0
